mask_test/strb2mask.v

module strb2mask (
    input wire clk,
    input wire rst,
    input wire [7:0] m_axi_wstrb,
    input wire i_valid,
    output reg [7:0] pmesh_mask, 
    output wire o_ready,
    input wire i_ready,
    output wire o_valid
);


localparam BASE_1B = 8'b1000_0000;
localparam BASE_2B = 8'b1100_0000;
localparam BASE_4B = 8'b1111_0000;
localparam BASE_8B = 8'b1111_1111;

localparam not_valid_state = 1'b0;
localparam valid_state = 1'b1;

reg [7:0] source_q;
reg [7:0] source_d;
reg [7:0] target [14:0];
reg [14:0] all_match; 
reg [14:0] part_match;
reg [7:0] output_mask;
reg [7:0] reverse_source;
reg [7:0] reverse_target [14:0];
reg valid_delay_stage1;
reg valid_delay_stage2;
integer i;
integer j, k;

// FSM for output valid control 
reg ovalid_state;
reg ovalid_state_next;


assign o_ready = (|all_match) & i_ready;

always@ (*) begin
    reverse_source[0] = source_q[7];
    reverse_source[1] = source_q[6];
    reverse_source[2] = source_q[5];
    reverse_source[3] = source_q[4];
    reverse_source[4] = source_q[3];
    reverse_source[5] = source_q[2];
    reverse_source[6] = source_q[1];
    reverse_source[7] = source_q[0];
    for (i = 0; i < 15; i = i + 1) begin
        reverse_target[i][0] = target[i][7];
        reverse_target[i][1] = target[i][6];
        reverse_target[i][2] = target[i][5];
        reverse_target[i][3] = target[i][4];
        reverse_target[i][4] = target[i][3];
        reverse_target[i][5] = target[i][2];
        reverse_target[i][6] = target[i][1];
        reverse_target[i][7] = target[i][0];
    end
end

always@ (*) begin  
     
    target[0] = BASE_8B >> 0; 
    target[1] = BASE_4B >> 4; 
    target[2] = BASE_2B >> 6; 
    target[3] = BASE_1B >> 7; 
    target[4] = BASE_1B >> 6;
    target[5] = BASE_2B >> 4;
    target[6] = BASE_1B >> 5;
    target[7] = BASE_1B >> 4;
    target[8] = BASE_4B >> 0;
    target[9] = BASE_2B >> 2;
    target[10] = BASE_1B >> 3;
    target[11] = BASE_1B >> 2;
    target[12] = BASE_2B >> 0;
    target[13] = BASE_1B >> 1;
    target[14] = BASE_1B >> 0;
    for (j = 0; j < 15; j = j + 1) begin
        all_match[j] = (source_q == target[j]);
    end
end

always@ (*) begin
    for (k = 0; k < 15; k = k + 1) begin
        part_match[k] = (source_q > target[k]) & (reverse_source > reverse_target[k]);
    end
end

always@ (*) begin
    if (~i_ready) begin
        if (i_valid) begin
            source_d = source_q;
            output_mask = output_mask;
        end
        else begin
            source_d = BASE_8B;
            output_mask = output_mask;
        end
    end
    else if ((|all_match)) begin
        source_d = m_axi_wstrb;
        casex (all_match)
            15'b????_????_????_??1: output_mask = target[0];
            15'b????_????_????_?1?: output_mask = target[1];
            15'b????_????_????_1??: output_mask = target[2];
            15'b????_????_???1_???: output_mask = target[3];
            15'b????_????_??1?_???: output_mask = target[4];
            15'b????_????_?1??_???: output_mask = target[5];
            15'b????_????_1???_???: output_mask = target[6];
            15'b????_???1_????_???: output_mask = target[7];
            15'b????_??1?_????_???: output_mask = target[8];
            15'b????_?1??_????_???: output_mask = target[9];
            15'b????_1???_????_???: output_mask = target[10];
            15'b???1_????_????_???: output_mask = target[11];
            15'b??1?_????_????_???: output_mask = target[12];
            15'b?1??_????_????_???: output_mask = target[13];
            15'b1???_????_????_???: output_mask = target[14];
            default:  output_mask = BASE_8B;
        endcase
    end
    else begin
        casex (part_match)
            15'b????_????_????_??1: begin output_mask = target[0]; source_d = source_q - target[0]; end
            15'b????_????_????_?1?: begin output_mask = target[1]; source_d = source_q - target[1]; end
            15'b????_????_????_1??: begin output_mask = target[2]; source_d = source_q - target[2]; end
            15'b????_????_???1_???: begin output_mask = target[3]; source_d = source_q - target[3]; end
            15'b????_????_??1?_???: begin output_mask = target[4]; source_d = source_q - target[4]; end
            15'b????_????_?1??_???: begin output_mask = target[5]; source_d = source_q - target[5]; end
            15'b????_????_1???_???: begin output_mask = target[6]; source_d = source_q - target[6]; end
            15'b????_???1_????_???: begin output_mask = target[7]; source_d = source_q - target[7]; end
            15'b????_??1?_????_???: begin output_mask = target[8]; source_d = source_q - target[8]; end
            15'b????_?1??_????_???: begin output_mask = target[9]; source_d = source_q - target[9]; end
            15'b????_1???_????_???: begin output_mask = target[10]; source_d = source_q - target[10]; end
            15'b???1_????_????_???: begin output_mask = target[11]; source_d = source_q - target[11]; end
            15'b??1?_????_????_???: begin output_mask = target[12]; source_d = source_q - target[12]; end
            15'b?1??_????_????_???: begin output_mask = target[13]; source_d = source_q - target[13]; end
            15'b1???_????_????_???: begin output_mask = target[14]; source_d = source_q - target[14]; end
            default:  begin output_mask = BASE_8B; source_d = source_q; end
        endcase
    end
end

always@ (posedge clk) begin
   if (rst) begin
        valid_delay_stage1 <= 0;
   end
   else begin
        valid_delay_stage1 <= i_valid & (o_ready | (|all_match));
   end
end

// FSN for output valid
always@(posedge clk) begin
    if (rst) ovalid_state <= not_valid_state;
    else ovalid_state <= ovalid_state_next;
end

always@ (*) begin
  if (ovalid_state == not_valid_state) begin
      if (valid_delay_stage1) ovalid_state_next = valid_state;
      else ovalid_state_next = ovalid_state;
  end
  else if (ovalid_state == valid_state) begin
      if (i_ready) ovalid_state_next = not_valid_state;
      else ovalid_state_next = ovalid_state;
  end
end

assign o_valid = (ovalid_state == valid_state);

always@ (posedge clk) begin 
    if (rst) begin
        pmesh_mask <= BASE_8B;
    end
    else begin
        pmesh_mask <= output_mask;
    end 
end

always@ (posedge clk) begin
    if (rst) begin
        source_q <= m_axi_wstrb;
    end
    else begin
        source_q <= source_d;
    end
end

endmodule

mask_test/testbench.v
`timescale 1ns / 1ns
//////////////////////////////////////////////////////////////////////////////////
// Company: 
// Engineer: 
// 
// Create Date: 2022/04/07 17:01:50
// Design Name: 
// Module Name: testbench
// Project Name: 
// Target Devices: 
// Tool Versions: 
// Description: 
// 
// Dependencies: 
// 
// Revision:
// Revision 0.01 - File Created
// Additional Comments:
// 
//////////////////////////////////////////////////////////////////////////////////
module testbench();


reg clk;
reg rst;
reg [7:0] m_axi_wstrb;
reg [7:0] input_array [3:0];
wire [7:0] pmesh_mask;
wire o_ready;
reg [1:0] counter;
reg valid;
wire o_valid;
reg [7:0] data_fetch; 
reg ready;
integer i;

localparam BASE_1B = 8'b1000_0000;
localparam BASE_2B = 8'b1100_0000;
localparam BASE_4B = 8'b1111_0000;
localparam BASE_8B = 8'b1111_1111;


strb2mask ins1
(
    .rst (rst),
    .clk (clk),
    .m_axi_wstrb (m_axi_wstrb),
    .pmesh_mask (pmesh_mask),
    .o_ready (o_ready),
    .i_valid (valid),
    .o_valid (o_valid),
    .i_ready (ready)
);

initial begin
    clk = 0;
    forever begin
       #5 clk = ~clk;
    end
end 

initial begin
    $display("dump start");
    $dumpfile("test.vcd");
    $dumpvars;
    #300 $finish;
    $display("dump finish");
end


always@ (posedge clk) begin
    if (rst) begin 
        m_axi_wstrb <= BASE_8B;
        counter <= 0;
        valid <= 1;
    end
    else if (o_ready & valid) begin
        valid <= valid;
        m_axi_wstrb <= input_array[counter];
        counter <= counter + 1;
    end
    else begin
        counter <= counter;
        m_axi_wstrb <= m_axi_wstrb;
        valid <= valid;
    end
end

always@ (posedge clk) begin
    if (rst) ready <= 1;
    else ready <= ~ready;
    
end

always@(posedge clk) begin
    if (rst) begin
        data_fetch<= 8'b0;
    end
    else if (o_valid) begin
        data_fetch <= pmesh_mask;
    end
end


initial begin
$display("simulation start");
input_array[0] <= BASE_4B;
input_array[1] <= 8'b0111_1110;
input_array[2] <= 8'b0110_0000;
input_array[3] <= BASE_8B;
$display("input array initialize complete");
rst <= 0;
@(negedge clk) rst <= 1;
@(negedge clk) rst <= 1;
@(negedge clk) rst <= 0;
end


endmodule

mask_test/test.vcd
$date
	Wed Apr 13 15:33:57 2022
$end
$version
	Icarus Verilog
$end
$timescale
	1ns
$end
$scope module testbench $end
$var wire 8 ! pmesh_mask [7:0] $end
$var wire 1 " o_valid $end
$var wire 1 # o_ready $end
$var reg 1 $ clk $end
$var reg 2 % counter [1:0] $end
$var reg 8 & data_fetch [7:0] $end
$var reg 8 ' m_axi_wstrb [7:0] $end
$var reg 1 ( ready $end
$var reg 1 ) rst $end
$var reg 1 * valid $end
$scope module ins1 $end
$var wire 1 $ clk $end
$var wire 1 ( i_ready $end
$var wire 1 * i_valid $end
$var wire 8 + m_axi_wstrb [7:0] $end
$var wire 1 # o_ready $end
$var wire 1 " o_valid $end
$var wire 1 ) rst $end
$var reg 15 , all_match [14:0] $end
$var reg 8 - output_mask [7:0] $end
$var reg 1 . ovalid_state $end
$var reg 1 / ovalid_state_next $end
$var reg 15 0 part_match [14:0] $end
$var reg 8 1 pmesh_mask [7:0] $end
$var reg 8 2 reverse_source [7:0] $end
$var reg 8 3 source_d [7:0] $end
$var reg 8 4 source_q [7:0] $end
$var reg 1 5 valid_delay_stage1 $end
$var integer 32 6 i [31:0] $end
$var integer 32 7 j [31:0] $end
$var integer 32 8 k [31:0] $end
$upscope $end
$upscope $end
$enddefinitions $end
#0
$dumpvars
bx 8
bx 7
bx 6
x5
bx 4
bx 3
bx 2
bx 1
bx 0
x/
x.
bx -
bx ,
bx +
x*
0)
x(
bx '
bx &
bx %
0$
x#
x"
bx !
$end
#5
1$
#10
1)
0$
#15
0"
0/
b0 &
1(
1*
b0 %
b11111111 '
b11111111 +
b11111111 !
b11111111 1
0.
05
1$
#20
0$
#25
1#
b11111111 -
b11111111 3
b111111111111110 0
b1111 8
b1 ,
b1111 7
b1111 6
b11111111 2
b11111111 4
1$
#30
0)
0$
#35
0#
1/
0(
b1 %
b11110000 '
b11110000 +
15
1$
#40
0$
#45
1"
1#
0/
b11110000 3
1.
1(
1$
#50
0$
#55
0#
b111111000000000 0
b1111 8
b100000000 ,
b1111 7
b1111 6
b1111 2
1/
0"
b11111111 &
0(
b10 %
b1111110 '
b1111110 +
b11110000 4
0.
1$
#60
0$
#65
1"
1#
0/
b11110000 -
b1111110 3
1.
1(
1$
#70
0$
#75
0#
b10111011110000 0
b1111 8
b0 ,
b1111 7
b1111 6
b1111110 2
1/
0"
0(
b11 %
b1100000 '
b1100000 +
b1111110 4
b11110000 !
b11110000 1
0.
1$
#80
0$
#85
1"
0/
b1111100 3
b10 -
05
1.
1(
1$
#90
0$
#95
b10111011100000 0
b1111 8
b1111 7
b1111 6
b111110 2
0"
b11110000 &
0(
b1111100 4
b10 !
b10 1
0.
1$
#100
0$
#105
b1110000 3
b1100 -
1(
1$
#110
0$
#115
b10111000000000 0
b1111 8
b1111 7
b1111 6
b1110 2
0(
b1110000 4
b1100 !
b1100 1
1$
#120
0$
#125
b1000000 3
b110000 -
1(
1$
#130
0$
#135
b0 0
b1111 8
b10000000000000 ,
b1111 7
b1111 6
b10 2
0(
b1000000 4
b110000 !
b110000 1
1$
#140
0$
#145
1#
1/
b1000000 -
b1100000 3
15
1(
1$
#150
0$
#155
0#
b10100000000000 0
b1111 8
b0 ,
b1111 7
b1111 6
b110 2
1"
0(
b0 %
b11111111 '
b11111111 +
b1100000 4
b1000000 !
b1000000 1
1.
1$
#160
0$
#165
0/
b1000000 3
b100000 -
05
1(
b1000000 &
1$
#170
0$
#175
b0 0
b1111 8
b10000000000000 ,
b1111 7
b1111 6
b10 2
0"
0(
b1000000 4
b100000 !
b100000 1
0.
1$
#180
0$
#185
1#
1/
b1000000 -
b11111111 3
15
1(
1$
#190
0$
#195
0#
b111111111111110 0
b1111 8
b1 ,
b1111 7
b1111 6
b11111111 2
1"
0(
b1 %
b11110000 '
b11110000 +
b11111111 4
b1000000 !
b1000000 1
1.
1$
#200
0$
#205
1#
0/
b11111111 -
b11110000 3
1(
1$
#210
0$
#215
0#
b111111000000000 0
b1111 8
b100000000 ,
b1111 7
b1111 6
b1111 2
1/
0"
0(
b10 %
b1111110 '
b1111110 +
b11110000 4
b11111111 !
b11111111 1
0.
1$
#220
0$
#225
1"
1#
0/
b11110000 -
b1111110 3
1.
1(
1$
#230
0$
#235
0#
b10111011110000 0
b1111 8
b0 ,
b1111 7
b1111 6
b1111110 2
1/
0"
b11111111 &
0(
b11 %
b1100000 '
b1100000 +
b1111110 4
b11110000 !
b11110000 1
0.
1$
#240
0$
#245
1"
0/
b1111100 3
b10 -
05
1.
1(
1$
#250
0$
#255
b10111011100000 0
b1111 8
b1111 7
b1111 6
b111110 2
0"
b11110000 &
0(
b1111100 4
b10 !
b10 1
0.
1$
#260
0$
#265
b1110000 3
b1100 -
1(
1$
#270
0$
#275
b10111000000000 0
b1111 8
b1111 7
b1111 6
b1110 2
0(
b1110000 4
b1100 !
b1100 1
1$
#280
0$
#285
b1000000 3
b110000 -
1(
1$
#290
0$
#295
b0 0
b1111 8
b10000000000000 ,
b1111 7
b1111 6
b10 2
0(
b1000000 4
b110000 !
b110000 1
1$
