mask_test/strb2mask.v

module strb2mask (
    input wire clk,
    input wire rst,
    input wire [7:0] m_axi_wstrb,
    output reg [7:0] pmesh_data_size,
    output reg [2:0] pmesh_addr,
    input wire s_channel_valid,
    output wire s_channel_ready,
    input wire d_channel_ready,
    output wire d_channel_valid
);


localparam BASE_1B = 8'b1000_0000;
localparam BASE_2B = 8'b1100_0000;
localparam BASE_4B = 8'b1111_0000;
localparam BASE_8B = 8'b1111_1111;

reg [7:0] source_q;
reg [7:0] source_d;
reg [7:0] input_data;
reg [7:0] target [14:0];
reg [14:0] all_match; 
reg [14:0] part_match;
reg [7:0] output_mask;
reg [7:0] pmesh_mask;
reg [7:0] reverse_source;
reg [7:0] reverse_target [14:0];

wire need_split;
wire split;
wire tx;
wire rx;
reg tx_delay_stage_1;
reg last_split;

integer i;
integer j, k;

// FSM for destination valid control 
localparam NOT_VALID = 0;
localparam VALID = 1;
reg valid_state;
reg valid_state_next;

//FSM for source ready control
reg [1:0] ready_state, next_ready_state;
localparam NOT_READY = 0;
localparam READY = 1;
localparam WAIT = 2;

assign tx = s_channel_ready & s_channel_valid;
assign rx = d_channel_ready & d_channel_valid;

assign split = (((last_split) & (!need_split)) | (need_split));
assign need_split = (|part_match) & ~(|all_match);

always@ (*) begin
    source_d = source_q;
end

always@ (*) begin // for split output 
    reverse_source[0] = source_q[7];
    reverse_source[1] = source_q[6];
    reverse_source[2] = source_q[5];
    reverse_source[3] = source_q[4];
    reverse_source[4] = source_q[3];
    reverse_source[5] = source_q[2];
    reverse_source[6] = source_q[1];
    reverse_source[7] = source_q[0];
    for (i = 0; i < 15; i = i + 1) begin
        reverse_target[i][0] = target[i][7];
        reverse_target[i][1] = target[i][6];
        reverse_target[i][2] = target[i][5];
        reverse_target[i][3] = target[i][4];
        reverse_target[i][4] = target[i][3];
        reverse_target[i][5] = target[i][2];
        reverse_target[i][6] = target[i][1];
        reverse_target[i][7] = target[i][0];
    end
end

always@ (*) begin  // target generate
    target[0] = BASE_8B >> 0; 
    target[1] = BASE_4B >> 4; 
    target[2] = BASE_2B >> 6; 
    target[3] = BASE_1B >> 7; 
    target[4] = BASE_1B >> 6;
    target[5] = BASE_2B >> 4;
    target[6] = BASE_1B >> 5;
    target[7] = BASE_1B >> 4;
    target[8] = BASE_4B >> 0;
    target[9] = BASE_2B >> 2;
    target[10] = BASE_1B >> 3;
    target[11] = BASE_1B >> 2;
    target[12] = BASE_2B >> 0;
    target[13] = BASE_1B >> 1;
    target[14] = BASE_1B >> 0;
    for (j = 0; j < 15; j = j + 1) begin
        all_match[j] = (source_q == target[j]);
    end
end

always@ (*) begin 
    for (k = 0; k < 15; k = k + 1) begin
        part_match[k] = (source_q > target[k]) & (reverse_source > reverse_target[k]);
    end
end

always@ (*) begin
    if ((|all_match)) begin
        input_data = m_axi_wstrb;
    end
    else if ((|part_match))begin
        casex (part_match)
            15'b????_????_????_??1: begin input_data = source_q - target[0]; end
            15'b????_????_????_?1?: begin input_data = source_q - target[1]; end
            15'b????_????_????_1??: begin input_data = source_q - target[2]; end
            15'b????_????_???1_???: begin input_data = source_q - target[3]; end
            15'b????_????_??1?_???: begin input_data = source_q - target[4]; end
            15'b????_????_?1??_???: begin input_data = source_q - target[5]; end
            15'b????_????_1???_???: begin input_data = source_q - target[6]; end
            15'b????_???1_????_???: begin input_data = source_q - target[7]; end
            15'b????_??1?_????_???: begin input_data = source_q - target[8]; end
            15'b????_?1??_????_???: begin input_data = source_q - target[9]; end
            15'b????_1???_????_???: begin input_data = source_q - target[10]; end
            15'b???1_????_????_???: begin input_data = source_q - target[11]; end
            15'b??1?_????_????_???: begin input_data = source_q - target[12]; end
            15'b?1??_????_????_???: begin input_data = source_q - target[13]; end
            15'b1???_????_????_???: begin input_data = source_q - target[14]; end
            default:  begin input_data = source_q; end
        endcase
    end
    else begin
        input_data = source_q;
    end
end

always@ (*) begin
    if ((|all_match)) begin
         casex (all_match)
            15'b????_????_????_??1: output_mask = target[0];
            15'b????_????_????_?1?: output_mask = target[1];
            15'b????_????_????_1??: output_mask = target[2];
            15'b????_????_???1_???: output_mask = target[3];
            15'b????_????_??1?_???: output_mask = target[4];
            15'b????_????_?1??_???: output_mask = target[5];
            15'b????_????_1???_???: output_mask = target[6];
            15'b????_???1_????_???: output_mask = target[7];
            15'b????_??1?_????_???: output_mask = target[8];
            15'b????_?1??_????_???: output_mask = target[9];
            15'b????_1???_????_???: output_mask = target[10];
            15'b???1_????_????_???: output_mask = target[11];
            15'b??1?_????_????_???: output_mask = target[12];
            15'b?1??_????_????_???: output_mask = target[13];
            15'b1???_????_????_???: output_mask = target[14];
            default:  output_mask = BASE_8B;
        endcase
    end
    else if ((|part_match)) begin
        casex (part_match)
            15'b????_????_????_??1: begin output_mask = target[0];end
            15'b????_????_????_?1?: begin output_mask = target[1];end
            15'b????_????_????_1??: begin output_mask = target[2];end
            15'b????_????_???1_???: begin output_mask = target[3];end
            15'b????_????_??1?_???: begin output_mask = target[4];end
            15'b????_????_?1??_???: begin output_mask = target[5];end
            15'b????_????_1???_???: begin output_mask = target[6];end
            15'b????_???1_????_???: begin output_mask = target[7];end
            15'b????_??1?_????_???: begin output_mask = target[8];end
            15'b????_?1??_????_???: begin output_mask = target[9];end
            15'b????_1???_????_???: begin output_mask = target[10];end
            15'b???1_????_????_???: begin output_mask = target[11];end
            15'b??1?_????_????_???: begin output_mask = target[12];end
            15'b?1??_????_????_???: begin output_mask = target[13];end
            15'b1???_????_????_???: begin output_mask = target[14];end
            default:  begin output_mask = BASE_8B; end
        endcase
    end
    else output_mask = pmesh_mask;
end


always@ (*) begin   
    casex (pmesh_mask)
        target[0]: begin pmesh_data_size = BASE_8B;  pmesh_addr = 0; end
        target[1]: begin pmesh_data_size = BASE_4B;  pmesh_addr = 4; end
        target[2]: begin pmesh_data_size = BASE_2B;  pmesh_addr = 6; end
        target[3]: begin pmesh_data_size = BASE_1B;  pmesh_addr = 7; end
        target[4]: begin pmesh_data_size = BASE_1B;  pmesh_addr = 6; end
        target[5]: begin pmesh_data_size = BASE_2B;  pmesh_addr = 4; end
        target[6]: begin pmesh_data_size = BASE_1B;  pmesh_addr = 5; end
        target[7]: begin pmesh_data_size = BASE_1B;  pmesh_addr = 4; end
        target[8]: begin pmesh_data_size = BASE_4B;  pmesh_addr = 0; end
        target[9]: begin pmesh_data_size = BASE_2B;  pmesh_addr = 2; end
        target[10]: begin pmesh_data_size = BASE_1B;  pmesh_addr = 3; end
        target[11]: begin pmesh_data_size = BASE_1B;  pmesh_addr = 2; end
        target[12]: begin pmesh_data_size = BASE_2B;  pmesh_addr = 0; end
        target[13]: begin pmesh_data_size = BASE_1B;  pmesh_addr = 1; end
        target[14]: begin pmesh_data_size = BASE_1B;  pmesh_addr = 0; end
        default: begin  pmesh_data_size = BASE_8B;  pmesh_addr = 0; end // is this the right default?
    endcase 
end


// FSN for output valid
always@(posedge clk) begin
    if (rst) valid_state <= NOT_VALID;
    else valid_state <= valid_state_next;
end

always@ (*) begin
  if (valid_state == NOT_VALID) begin
      if (tx_delay_stage_1) valid_state_next = VALID;
      else valid_state_next = valid_state;
  end
  else if (valid_state == VALID) begin
      if (tx_delay_stage_1| split) valid_state_next = VALID;
      else if (d_channel_ready) valid_state_next = NOT_VALID;
      else valid_state_next = valid_state;
  end
end

assign d_channel_valid = (valid_state == VALID);


always@(posedge clk) begin
    if (rst)begin
        tx_delay_stage_1 <= 0;
        last_split <= 0;

    end
    else begin
        tx_delay_stage_1 <= tx;
        last_split <= need_split;
    end
end

always@ (posedge clk) begin
    if (rst) ready_state <= NOT_READY;
    else ready_state <= next_ready_state;
end

always@(*) begin
    if (ready_state == NOT_READY) begin
        if (d_channel_ready && ~need_split) next_ready_state = READY;
        else next_ready_state = NOT_READY;
    end
    else if (ready_state == READY) begin
        if (tx) next_ready_state = WAIT;
        else next_ready_state = READY;
    end
    else if (ready_state == WAIT) begin
        if (rx) next_ready_state = NOT_READY;
        else next_ready_state = WAIT;
    end
    else next_ready_state = ready_state;
end

assign s_channel_ready = (ready_state == READY) ? 1'b1 : 1'b0;

always@ (posedge clk) begin 
    if (rst) begin
        pmesh_mask <= BASE_8B;
    end
    else begin
        pmesh_mask <= output_mask;
    end 
end
always@ (posedge clk) begin
    if (rst) source_q <= BASE_8B;
    else if (tx | (need_split & rx)) source_q <= input_data;
    else source_q <= source_d;
end

endmodule

mask_test/testbench.v
`timescale 1ns / 1ns
//////////////////////////////////////////////////////////////////////////////////
// Company: 
// Engineer: 
// 
// Create Date: 2022/04/07 17:01:50
// Design Name: 
// Module Name: testbench
// Project Name: 
// Target Devices: 
// Tool Versions: 
// Description: 
// 
// Dependencies: 
// 
// Revision:
// Revision 0.01 - File Created
// Additional Comments:
// 
//////////////////////////////////////////////////////////////////////////////////
module testbench();


reg clk;
reg rst;
reg [7:0] m_axi_wstrb;
wire [7:0] data_size;
wire [2:0] addr;

reg [7:0] input_array [3:0];
reg [1:0] counter;


wire s_channel_valid;
wire s_channel_ready;
wire d_channel_ready;
wire d_channel_valid;

reg fifo_has_packet;

integer i;

localparam BASE_1B = 8'b1000_0000;
localparam BASE_2B = 8'b1100_0000;
localparam BASE_4B = 8'b1111_0000;
localparam BASE_8B = 8'b1111_1111;

localparam NOT_VALID = 0;
localparam VALID = 1;
reg state, next_state;

reg [1:0] fake_ready_state, fake_ready_next_state;

strb2mask ins1
(
    .rst (rst),
    .clk (clk),
    .m_axi_wstrb (m_axi_wstrb),
    //.pmesh_mask (pmesh_mask),
    .pmesh_data_size (data_size),
    .pmesh_addr (addr),
    .s_channel_ready (s_channel_ready),
    .s_channel_valid (s_channel_valid),
    .d_channel_valid (d_channel_valid),
    .d_channel_ready (d_channel_ready)
);

initial begin
    clk = 0;
    forever begin
       #5 clk = ~clk;
    end
end 

initial begin
    $display("dump start");
    $dumpfile("test.vcd");
    $dumpvars;
    #1000 $finish;
    $display("dump finish");
end



// input counter control
always@ (posedge clk) begin
    if (rst) counter <= 0;
    else if (s_channel_ready & s_channel_valid) counter <= counter + 1;
    else counter <= counter;
end

always@(*) begin
    m_axi_wstrb = input_array[counter];
end



// valid control state machine 

assign s_channel_valid = (state == VALID);
always@(posedge clk) begin
    if (rst) state <= NOT_VALID;
    else state <= next_state;
end

always@(*) begin
    if (fifo_has_packet) next_state <= VALID;
    else if (~fifo_has_packet) next_state <= NOT_VALID;
end


//ready control

always@ (posedge clk) begin
    if (rst) fake_ready_state <= 2'b00;
    else fake_ready_state <= fake_ready_next_state;
end

always@ (*) begin
    if (fake_ready_state == 2'b00)
        fake_ready_next_state = 2'b01;
    else if (fake_ready_state == 2'b01)
        fake_ready_next_state = 2'b10;
    else if (fake_ready_state == 2'b10) begin
        if (d_channel_ready & d_channel_valid) 
            fake_ready_next_state = 2'b11;
        else fake_ready_next_state = fake_ready_state;
    end
    else if (fake_ready_state == 2'b11) 
        fake_ready_next_state = 2'b00;
    else 
        fake_ready_next_state = fake_ready_state;
end

assign d_channel_ready = (fake_ready_state == 2'b10) ? 1'b1 : 1'b0;

//assign d_channel_ready = 1;



initial begin
$display("simulation start");
input_array[0] <= BASE_4B;
input_array[1] <= 8'b0111_1110;;
input_array[2] <= BASE_4B;
input_array[3] <= 8'b0111_1111;
$display("input array initialize complete");
rst <= 0;
@(negedge clk) rst <= 1;
fifo_has_packet <= 1;
@(negedge clk) rst <= 1;
@(negedge clk) rst <= 0;
/*
repeat(6) @(posedge clk);
@(posedge clk) fifo_has_packet <= 0;

repeat(5) @(posedge clk);
@(posedge clk)fifo_has_packet <= 1;

repeat(6) @(posedge clk);
@(posedge clk) fifo_has_packet <= 0;

repeat(5) @(posedge clk);
@(posedge clk)fifo_has_packet <= 1;

*/

end


endmodule

mask_test/test.vcd
$date
	Fri May 13 22:56:25 2022
$end
$version
	Icarus Verilog
$end
$timescale
	1ns
$end
$scope module testbench $end
$var wire 1 ! s_channel_valid $end
$var wire 1 " s_channel_ready $end
$var wire 8 # data_size [7:0] $end
$var wire 1 $ d_channel_valid $end
$var wire 1 % d_channel_ready $end
$var wire 3 & addr [2:0] $end
$var reg 1 ' clk $end
$var reg 2 ( counter [1:0] $end
$var reg 2 ) fake_ready_next_state [1:0] $end
$var reg 2 * fake_ready_state [1:0] $end
$var reg 1 + fifo_has_packet $end
$var reg 8 , m_axi_wstrb [7:0] $end
$var reg 1 - next_state $end
$var reg 1 . rst $end
$var reg 1 / state $end
$scope module ins1 $end
$var wire 1 ' clk $end
$var wire 1 % d_channel_ready $end
$var wire 8 0 m_axi_wstrb [7:0] $end
$var wire 1 1 need_split $end
$var wire 1 . rst $end
$var wire 1 2 rx $end
$var wire 1 ! s_channel_valid $end
$var wire 1 3 split $end
$var wire 1 4 tx $end
$var wire 1 " s_channel_ready $end
$var wire 1 $ d_channel_valid $end
$var reg 15 5 all_match [14:0] $end
$var reg 8 6 input_data [7:0] $end
$var reg 1 7 last_split $end
$var reg 2 8 next_ready_state [1:0] $end
$var reg 8 9 output_mask [7:0] $end
$var reg 15 : part_match [14:0] $end
$var reg 3 ; pmesh_addr [2:0] $end
$var reg 8 < pmesh_data_size [7:0] $end
$var reg 8 = pmesh_mask [7:0] $end
$var reg 2 > ready_state [1:0] $end
$var reg 8 ? reverse_source [7:0] $end
$var reg 8 @ source_d [7:0] $end
$var reg 8 A source_q [7:0] $end
$var reg 1 B tx_delay_stage_1 $end
$var reg 1 C valid_state $end
$var reg 1 D valid_state_next $end
$var integer 32 E i [31:0] $end
$var integer 32 F j [31:0] $end
$var integer 32 G k [31:0] $end
$upscope $end
$upscope $end
$enddefinitions $end
#0
$dumpvars
bx G
bx F
bx E
xD
xC
xB
bx A
bx @
bx ?
bx >
bx =
bx <
bx ;
bx :
bx 9
bx 8
x7
bx 6
bx 5
x4
x3
x2
x1
bx 0
x/
0.
x-
bx ,
x+
bx *
bx )
bx (
0'
bx &
x%
x$
bx #
x"
x!
$end
#5
1'
#10
1-
1+
1.
0'
#15
03
01
b11110000 6
0%
04
b11110000 ,
b11110000 0
b111111111111110 :
b1111 G
b1 5
b1111 F
b1111 E
b11111111 ?
b11111111 @
b0 &
b0 ;
b11111111 #
b11111111 <
b11111111 9
b0 8
0"
0D
02
b1 )
b0 *
0!
0/
b0 (
b11111111 A
b11111111 =
b0 >
07
0B
0$
0C
1'
#20
0'
#25
1'
#30
0.
0'
#35
b10 )
b1 *
1!
1/
1'
#40
0'
#45
b1 8
1%
b10 *
1'
#50
0'
#55
b10 8
14
1"
b1 >
1'
#60
0'
#65
04
b11110000 9
1D
0"
b1111110 6
b111111000000000 :
b1111 G
b100000000 5
b1111 F
b1111 E
b1111 ?
b11110000 @
b1111110 ,
b1111110 0
1B
b10 >
b11110000 A
b1 (
1'
#70
0'
#75
b0 8
b11110000 #
b11110000 <
0D
12
b11 )
b11110000 =
0B
1$
1C
1'
#80
0'
#85
02
b0 )
0%
0$
0C
b0 >
b11 *
1'
#90
0'
#95
b1 )
b0 *
1'
#100
0'
#105
b10 )
b1 *
1'
#110
0'
#115
b1 8
1%
b10 *
1'
#120
0'
#125
b10 8
14
1"
b1 >
1'
#130
0'
#135
13
11
b10 9
04
b11110000 ,
b11110000 0
b1111100 6
b10111011110000 :
b1111 G
b0 5
b1111 F
b1111 E
b1111110 ?
b1111110 @
0"
1D
b10 (
b1111110 A
b10 >
1B
1'
#140
0'
#145
b0 8
12
b11 )
b110 &
b110 ;
b10000000 #
b10000000 <
1$
1C
17
0B
b10 =
1'
#150
0'
#155
02
b1100 9
b0 )
0%
b1110000 6
b10111011100000 :
b1111 G
b1111 F
b1111 E
b111110 ?
b1111100 @
b11 *
b1111100 A
b0 >
1'
#160
0'
#165
b100 &
b100 ;
b11000000 #
b11000000 <
b1 )
b1100 =
b0 *
1'
#170
0'
#175
b10 )
b1 *
1'
#180
0'
#185
12
b11 )
1%
b10 *
1'
#190
0'
#195
02
b110000 9
b0 )
0%
b1000000 6
b10111000000000 :
b1111 G
b1111 F
b1111 E
b1110 ?
b1110000 @
b11 *
b1110000 A
1'
#200
0'
#205
b10 &
b10 ;
b1 )
b110000 =
b0 *
1'
#210
0'
#215
b10 )
b1 *
1'
#220
0'
#225
12
b11 )
1%
b10 *
1'
#230
0'
#235
13
02
01
b1000000 9
b0 )
0%
b11110000 6
b0 :
b1111 G
b10000000000000 5
b1111 F
b1111 E
b10 ?
b1000000 @
b11 *
b1000000 A
1'
#240
0'
#245
03
b1 &
b1 ;
b10000000 #
b10000000 <
b1 )
07
b1000000 =
b0 *
1'
#250
0'
#255
b10 )
b1 *
1'
#260
0'
#265
12
b1 8
0D
b11 )
1%
b10 *
1'
#270
0'
#275
b10 8
14
0%
1"
02
b0 )
b11 *
b1 >
0$
0C
1'
#280
0'
#285
04
b11110000 9
1D
0"
b1111111 6
b111111000000000 :
b1111 G
b100000000 5
b1111 F
b1111 E
b1111 ?
b11110000 @
b1111111 ,
b1111111 0
b1 )
1B
b10 >
b11110000 A
b11 (
b0 *
1'
#290
0'
#295
b0 &
b0 ;
b11110000 #
b11110000 <
b10 )
b1 *
b11110000 =
0B
1$
1C
1'
#300
0'
#305
b0 8
12
0D
b11 )
1%
b10 *
1'
#310
0'
#315
0%
b0 8
02
b0 )
b11 *
b0 >
0$
0C
1'
#320
0'
#325
b1 )
b0 *
1'
#330
0'
#335
b10 )
b1 *
1'
#340
0'
#345
b1 8
1%
b10 *
1'
#350
0'
#355
b10 8
14
1"
b1 >
1'
#360
0'
#365
13
11
04
b1111 9
1D
0"
b1110000 6
b10111011111110 :
b1111 G
b0 5
b1111 F
b1111 E
b11111110 ?
b1111111 @
b11110000 ,
b11110000 0
1B
b10 >
b1111111 A
b0 (
1'
#370
0'
#375
b0 8
b100 &
b100 ;
12
b11 )
b1111 =
17
0B
1$
1C
1'
#380
0'
#385
b110000 9
02
b1000000 6
b10111000000000 :
b1111 G
b1111 F
b1111 E
b1110 ?
b1110000 @
b0 )
0%
b0 >
b1110000 A
b11 *
1'
#390
0'
#395
b1 )
b10 &
b10 ;
b11000000 #
b11000000 <
b0 *
b110000 =
1'
#400
0'
#405
b10 )
b1 *
1'
#410
0'
#415
12
b11 )
1%
b10 *
1'
#420
0'
#425
13
01
b1000000 9
02
b11110000 6
b0 :
b1111 G
b10000000000000 5
b1111 F
b1111 E
b10 ?
b1000000 @
b0 )
0%
b1000000 A
b11 *
1'
#430
0'
#435
03
b1 )
b1 &
b1 ;
b10000000 #
b10000000 <
b0 *
b1000000 =
07
1'
#440
0'
#445
b10 )
b1 *
1'
#450
0'
#455
12
b1 8
0D
b11 )
1%
b10 *
1'
#460
0'
#465
b10 8
14
02
1"
b0 )
0%
0$
0C
b1 >
b11 *
1'
#470
0'
#475
b1111110 6
b11110000 9
04
b1 )
b1111110 ,
b1111110 0
b111111000000000 :
b1111 G
b100000000 5
b1111 F
b1111 E
b1111 ?
b11110000 @
0"
1D
b0 *
b1 (
b11110000 A
b10 >
1B
1'
#480
0'
#485
b0 &
b0 ;
b11110000 #
b11110000 <
b10 )
1$
1C
0B
b11110000 =
b1 *
1'
#490
0'
#495
b0 8
12
0D
b11 )
1%
b10 *
1'
#500
0'
#505
02
b0 )
0%
0$
0C
b0 >
b11 *
1'
#510
0'
#515
b1 )
b0 *
1'
#520
0'
#525
b10 )
b1 *
1'
#530
0'
#535
b1 8
1%
b10 *
1'
#540
0'
#545
b10 8
14
1"
b1 >
1'
#550
0'
#555
13
11
b10 9
04
b11110000 ,
b11110000 0
b1111100 6
b10111011110000 :
b1111 G
b0 5
b1111 F
b1111 E
b1111110 ?
b1111110 @
0"
1D
b10 (
b1111110 A
b10 >
1B
1'
#560
0'
#565
b0 8
12
b11 )
b110 &
b110 ;
b10000000 #
b10000000 <
1$
1C
17
0B
b10 =
1'
#570
0'
#575
02
b1100 9
b0 )
0%
b1110000 6
b10111011100000 :
b1111 G
b1111 F
b1111 E
b111110 ?
b1111100 @
b11 *
b1111100 A
b0 >
1'
#580
0'
#585
b100 &
b100 ;
b11000000 #
b11000000 <
b1 )
b1100 =
b0 *
1'
#590
0'
#595
b10 )
b1 *
1'
#600
0'
#605
12
b11 )
1%
b10 *
1'
#610
0'
#615
02
b110000 9
b0 )
0%
b1000000 6
b10111000000000 :
b1111 G
b1111 F
b1111 E
b1110 ?
b1110000 @
b11 *
b1110000 A
1'
#620
0'
#625
b10 &
b10 ;
b1 )
b110000 =
b0 *
1'
#630
0'
#635
b10 )
b1 *
1'
#640
0'
#645
12
b11 )
1%
b10 *
1'
#650
0'
#655
13
02
01
b1000000 9
b0 )
0%
b11110000 6
b0 :
b1111 G
b10000000000000 5
b1111 F
b1111 E
b10 ?
b1000000 @
b11 *
b1000000 A
1'
#660
0'
#665
03
b1 &
b1 ;
b10000000 #
b10000000 <
b1 )
07
b1000000 =
b0 *
1'
#670
0'
#675
b10 )
b1 *
1'
#680
0'
#685
12
b1 8
0D
b11 )
1%
b10 *
1'
#690
0'
#695
b10 8
14
0%
1"
02
b0 )
b11 *
b1 >
0$
0C
1'
#700
0'
#705
04
b11110000 9
1D
0"
b1111111 6
b111111000000000 :
b1111 G
b100000000 5
b1111 F
b1111 E
b1111 ?
b11110000 @
b1111111 ,
b1111111 0
b1 )
1B
b10 >
b11110000 A
b11 (
b0 *
1'
#710
0'
#715
b0 &
b0 ;
b11110000 #
b11110000 <
b10 )
b1 *
b11110000 =
0B
1$
1C
1'
#720
0'
#725
b0 8
12
0D
b11 )
1%
b10 *
1'
#730
0'
#735
0%
b0 8
02
b0 )
b11 *
b0 >
0$
0C
1'
#740
0'
#745
b1 )
b0 *
1'
#750
0'
#755
b10 )
b1 *
1'
#760
0'
#765
b1 8
1%
b10 *
1'
#770
0'
#775
b10 8
14
1"
b1 >
1'
#780
0'
#785
13
11
04
b1111 9
1D
0"
b1110000 6
b10111011111110 :
b1111 G
b0 5
b1111 F
b1111 E
b11111110 ?
b1111111 @
b11110000 ,
b11110000 0
1B
b10 >
b1111111 A
b0 (
1'
#790
0'
#795
b0 8
b100 &
b100 ;
12
b11 )
b1111 =
17
0B
1$
1C
1'
#800
0'
#805
b110000 9
02
b1000000 6
b10111000000000 :
b1111 G
b1111 F
b1111 E
b1110 ?
b1110000 @
b0 )
0%
b0 >
b1110000 A
b11 *
1'
#810
0'
#815
b1 )
b10 &
b10 ;
b11000000 #
b11000000 <
b0 *
b110000 =
1'
#820
0'
#825
b10 )
b1 *
1'
#830
0'
#835
12
b11 )
1%
b10 *
1'
#840
0'
#845
13
01
b1000000 9
02
b11110000 6
b0 :
b1111 G
b10000000000000 5
b1111 F
b1111 E
b10 ?
b1000000 @
b0 )
0%
b1000000 A
b11 *
1'
#850
0'
#855
03
b1 )
b1 &
b1 ;
b10000000 #
b10000000 <
b0 *
b1000000 =
07
1'
#860
0'
#865
b10 )
b1 *
1'
#870
0'
#875
12
b1 8
0D
b11 )
1%
b10 *
1'
#880
0'
#885
b10 8
14
02
1"
b0 )
0%
0$
0C
b1 >
b11 *
1'
#890
0'
#895
b1111110 6
b11110000 9
04
b1 )
b1111110 ,
b1111110 0
b111111000000000 :
b1111 G
b100000000 5
b1111 F
b1111 E
b1111 ?
b11110000 @
0"
1D
b0 *
b1 (
b11110000 A
b10 >
1B
1'
#900
0'
#905
b0 &
b0 ;
b11110000 #
b11110000 <
b10 )
1$
1C
0B
b11110000 =
b1 *
1'
#910
0'
#915
b0 8
12
0D
b11 )
1%
b10 *
1'
#920
0'
#925
02
b0 )
0%
0$
0C
b0 >
b11 *
1'
#930
0'
#935
b1 )
b0 *
1'
#940
0'
#945
b10 )
b1 *
1'
#950
0'
#955
b1 8
1%
b10 *
1'
#960
0'
#965
b10 8
14
1"
b1 >
1'
#970
0'
#975
13
11
b10 9
04
b11110000 ,
b11110000 0
b1111100 6
b10111011110000 :
b1111 G
b0 5
b1111 F
b1111 E
b1111110 ?
b1111110 @
0"
1D
b10 (
b1111110 A
b10 >
1B
1'
#980
0'
#985
b0 8
12
b11 )
b110 &
b110 ;
b10000000 #
b10000000 <
1$
1C
17
0B
b10 =
1'
#990
0'
#995
02
b1100 9
b0 )
0%
b1110000 6
b10111011100000 :
b1111 G
b1111 F
b1111 E
b111110 ?
b1111100 @
b11 *
b1111100 A
b0 >
1'
